gym_pusht/__init__.py
gym_pusht/envs/__init__.py
gym_pusht/envs/pusht.py
gym_pusht/envs/pymunk_override.py
gym_pusht-0.1.6.dist-info/METADATA
gym_pusht-0.1.6.dist-info/WHEEL
gym_pusht-0.1.6.dist-info/licenses/LICENSE
gym_pusht-0.1.6.dist-info/RECORD
